quantpack/__init__.py
quantpack/backtest/__init__.py
quantpack/backtest/vanilla.py
quantpack/metrics/__init__.py
quantpack/metrics/ratios.py
quantpack/metrics/reactivity.py
quantpack/metrics/returns.py
quantpack/metrics/risk.py
quantpack/metrics/volatility.py
quantpack/utils/__init__.py
quantpack/visuals/__init__.py
quantpack-0.0.1.dist-info/LICENSE.md
quantpack-0.0.1.dist-info/METADATA
quantpack-0.0.1.dist-info/WHEEL
quantpack-0.0.1.dist-info/top_level.txt
quantpack-0.0.1.dist-info/RECORD
